lil_url
test
